zmongo/__init__.py
zmongo/filter.py
zmongo_filter-0.0.6.dist-info/METADATA
zmongo_filter-0.0.6.dist-info/WHEEL
zmongo_filter-0.0.6.dist-info/top_level.txt
zmongo_filter-0.0.6.dist-info/RECORD
