Metadata-Version: 2.1
Name: zmongo-filter
Version: 0.0.6
Summary: Mongo Filter for ReferenceField - EmbeddedDocumentField
Home-page: https://gitlab.com/Luisff3rnando/mongo-filter
Author: Luis Meza
Author-email: luisfernandomeza@hotmail.es
License: MIT
Platform: Any
Classifier: Programming Language :: Python :: 3
Classifier: License :: OSI Approved :: MIT License
Classifier: Operating System :: OS Independent
Requires-Python: >=3.0
Requires-Dist: setuptools
